README.md
setup.py
census_downloader/__init__.py
census_downloader/census_2000_api.py
census_downloader/census_2000_intpt.py
census_downloader/cli.py
census_downloader/download.py
census_downloader.egg-info/PKG-INFO
census_downloader.egg-info/SOURCES.txt
census_downloader.egg-info/dependency_links.txt
census_downloader.egg-info/entry_points.txt
census_downloader.egg-info/requires.txt
census_downloader.egg-info/top_level.txt