Metadata-Version: 2.1
Name: census-downloader
Version: 1.3.0
Summary: Clean way to download census data.
Home-page: https://github.com/kavigupta/census-downloader
Author: Kavi Gupta
Author-email: censusdownloader@kavigupta.org
Classifier: Programming Language :: Python :: 3.6
Classifier: Programming Language :: Python :: 3.7
Classifier: Programming Language :: Python :: 3.8
Classifier: Operating System :: OS Independent
Requires-Python: >=3.6
